riscv_test/riscv_test.srcs/sources_1/new/top.v
module riscv_pipeline_basic (
    input clk,
    input reset
);

    // Instruction memory, register file, SVR_WVR, and data memory
    reg [31:0] instruction_memory [0:255];  // 256 instructions
    reg [31:0] data_memory [0:255];         // 256 words of data
    reg [31:0] register_file [0:31];        // 32 GPR
    reg [31:0] SVR_WVR [0:31];              // 16 SVR, 16 WVR

    // Pipeline registers
    reg [31:0] IF_ID_instr, IF_ID_PC;
    
    reg [31:0] ID_EX_PC, ID_EX_instr;
    reg [31:0] ID_EX_read_data;
    reg [4:0] ID_EX_rs1, ID_EX_rd;
    reg [0:0] ID_EX_hint;
    reg [11:0] ID_EX_imm;
    reg [2:0] ID_EX_funct3;
    
    reg [31:0] EX_MEM_alu_result;
    reg [4:0]  EX_MEM_rd;
    reg [0:0] EX_MEM_hint;
    reg [2:0] EX_MEM_funct3;
    
    reg [31:0] MEM_WB_alu_result;
    reg [4:0]  MEM_WB_rd;
    reg [2:0] MEM_WB_funct3;
    reg [31:0] MEM_WB_memOut [15:0];

    // Program Counter (PC)
    reg [31:0] PC;

    // Iterator 
    integer i;

    // Initialize register file and data memory 
    initial begin
        PC = 0;
       
        // Initialize the register file
        for (i = 0; i < 32; i = i + 1) begin
            register_file[i] <= i;
        end
        
        // Initialize the data memory
        for (i = 0; i < 256; i = i + 1) begin
            data_memory[i] <= i;
        end
    end

    // FETCH stage
    always @(posedge clk or posedge reset) begin
        if (reset) begin
            IF_ID_instr <= 0;
            IF_ID_PC <= 0;
        end else begin
            IF_ID_instr <= instruction_memory[PC[7:0]];  // Fetch instruction
            IF_ID_PC <= PC;
            PC <= PC + 1;  // Increment PC
        end
    end

    // DECODE stage
    wire [6:0] opcode = IF_ID_instr[6:0];
    wire [4:0] rd = {(IF_ID_instr[0]), IF_ID_instr[10:7]};
    wire [0:0] hint = IF_ID_instr[11];
    wire [2:0] funct3 = IF_ID_instr[14:12];
    wire [4:0] rs1 = IF_ID_instr[19:15];
    wire [11:0] imm = IF_ID_instr[31:20];

    always @(posedge clk or posedge reset) begin
        if (reset) begin
            ID_EX_PC <= 0;
            ID_EX_instr <= 0;
        end else begin
            ID_EX_PC <= IF_ID_PC;
            ID_EX_instr <= IF_ID_instr;
            ID_EX_rd <= rd;
            ID_EX_read_data <= register_file[rs1];
            ID_EX_rs1 <= rs1;
            ID_EX_hint <= hint;
            ID_EX_imm <= imm;
            ID_EX_funct3 <= funct3;
        end
    end

    // EXECUTE stage
    wire [31:0] alu_input1 = ID_EX_read_data;
    wire [31:0] alu_input2 = ID_EX_imm;
    reg [31:0] alu_result = 0;

    always @(*) begin
        alu_result = alu_input1 + alu_input2;  
    end

    always @(posedge clk or posedge reset) begin
        if (reset) begin
            EX_MEM_alu_result <= 0;
        end else begin
            EX_MEM_alu_result <= alu_result;
            EX_MEM_rd <= ID_EX_rd;
            EX_MEM_hint <= ID_EX_hint;
            EX_MEM_funct3 <= ID_EX_funct3;
        end
    end

    // MEMORY stage
    reg [31:0] memOut [15:0];
    
    always @ (*) begin
        case(EX_MEM_funct3)
            3'b001: begin 
                    memOut[EX_MEM_rd[3:0]] = data_memory[EX_MEM_alu_result%256];
                end
            3'b010: begin
                    for (i = 0; i < 4; i = i + 1) begin
                        memOut[(EX_MEM_rd[3:0] + i)%16] = data_memory[(EX_MEM_alu_result + i)%256];
                    end
                end
            3'b100: begin
                    for (i = 0; i < 16; i = i + 1) begin
                        memOut[(EX_MEM_rd[3:0] + i)%16] = data_memory[(EX_MEM_alu_result + i)%256];
                    end
                end
        endcase
    end
    
    always @(posedge clk or posedge reset) begin
        if (reset) begin
            MEM_WB_alu_result <= 0;
        end else begin
            MEM_WB_alu_result <= EX_MEM_alu_result;
            MEM_WB_rd <= EX_MEM_rd;
            MEM_WB_funct3 <= EX_MEM_funct3;
            
            for (i = 0; i < 16; i = i + 1) begin
                MEM_WB_memOut[i] <= memOut[i];
            end
        end
    end

    // WRITEBACK stage
    reg [3:0] SVR_WVR_Addr; 
    
    always @ (*) begin
        if (!reset) begin   
            case(MEM_WB_funct3)
                3'b001: begin 
                        SVR_WVR[MEM_WB_rd] = MEM_WB_memOut[MEM_WB_rd[3:0]];
                    end
                3'b010: begin
                    for (i = 0; i < 4; i = i + 1) begin
                        SVR_WVR_Addr = ((MEM_WB_rd[3:0] + i)%16);
                        SVR_WVR[{MEM_WB_rd[4],SVR_WVR_Addr}] = MEM_WB_memOut[(MEM_WB_rd[3:0] + i)%16];
                    end
                end
                3'b100: begin
                    for (i = 0; i < 16; i = i + 1) begin
                        SVR_WVR_Addr = ((MEM_WB_rd[3:0] + i)%16);
                        SVR_WVR[{MEM_WB_rd[4],SVR_WVR_Addr}] = MEM_WB_memOut[(MEM_WB_rd[3:0] + i)%16];
                    end
                end
            endcase
        end 
    end

endmodule

riscv_test/riscv_test.srcs/sim_1/new/tb_riscv_pipeline.v
`timescale 1ns / 1ps

module tb_riscv_pipeline_basic;
    reg clk;
    reg reset;

    // Instantiate the RISC-V pipeline module
    riscv_pipeline_basic uut (
        .clk(clk),
        .reset(reset)
    );
    
    // Probe Signals 
    wire [31:0] PC;
    wire [31:0] IF_ID_instr;
    wire [31:0] IF_ID_PC;
    
    wire [31:0] ID_EX_PC;
    wire [31:0] ID_EX_instr;
    wire [31:0] ID_EX_read_data;
    wire [4:0]  ID_EX_rs1;
    wire [4:0]  ID_EX_rd;
    wire [0:0]  ID_EX_hint;
    wire [11:0] ID_EX_imm;
    wire [2:0]  ID_EX_funct3;
    
    wire [31:0] EX_MEM_alu_result;
    wire [4:0]  EX_MEM_rd;
    wire        EX_MEM_hint;
    wire [2:0]  EX_MEM_funct3;
    
    wire [31:0] MEM_WB_alu_result;
    wire [4:0]  MEM_WB_rd;

    wire [31:0] MEM_WB_memOut [15:0];
    wire [31:0] SVR_WVR [0:31];
    
    assign PC = uut.PC;
    assign IF_ID_instr = uut.IF_ID_instr;
    assign IF_ID_PC = uut.IF_ID_PC;
    
    assign ID_EX_PC = uut.ID_EX_PC;
    assign ID_EX_instr = uut.ID_EX_instr;
    assign ID_EX_read_data = uut.ID_EX_read_data;
    assign ID_EX_rs1 = uut.ID_EX_rs1;
    assign ID_EX_rd = uut.ID_EX_rd;
    assign ID_EX_hint = uut.ID_EX_hint;
    assign ID_EX_imm = uut.ID_EX_imm;
    assign ID_EX_funct3 = uut.ID_EX_funct3;
    
    assign EX_MEM_alu_result = uut.EX_MEM_alu_result;
    assign EX_MEM_rd = uut.EX_MEM_rd;
    assign EX_MEM_hint = uut.EX_MEM_hint;
    assign EX_MEM_funct3 = uut.EX_MEM_funct3;
    
    assign MEM_WB_alu_result = uut.MEM_WB_alu_result;
    assign MEM_WB_rd = uut.MEM_WB_rd;

    assign MEM_WB_memOut[0] = uut.MEM_WB_memOut[0];
    assign MEM_WB_memOut[1] = uut.MEM_WB_memOut[1];
    assign MEM_WB_memOut[2] = uut.MEM_WB_memOut[2];
    assign MEM_WB_memOut[3] = uut.MEM_WB_memOut[3];
    assign MEM_WB_memOut[4] = uut.MEM_WB_memOut[4];
    assign MEM_WB_memOut[5] = uut.MEM_WB_memOut[5];
    assign MEM_WB_memOut[6] = uut.MEM_WB_memOut[6];
    assign MEM_WB_memOut[7] = uut.MEM_WB_memOut[7];
    assign MEM_WB_memOut[8] = uut.MEM_WB_memOut[8];
    assign MEM_WB_memOut[9] = uut.MEM_WB_memOut[9];
    assign MEM_WB_memOut[10] = uut.MEM_WB_memOut[10];
    assign MEM_WB_memOut[11] = uut.MEM_WB_memOut[11];
    assign MEM_WB_memOut[12] = uut.MEM_WB_memOut[12];
    assign MEM_WB_memOut[13] = uut.MEM_WB_memOut[13];
    assign MEM_WB_memOut[14] = uut.MEM_WB_memOut[14];
    assign MEM_WB_memOut[15] = uut.MEM_WB_memOut[15];

    assign SVR_WVR[0] = uut.SVR_WVR[0];
    assign SVR_WVR[1] = uut.SVR_WVR[1];
    assign SVR_WVR[2] = uut.SVR_WVR[2];
    assign SVR_WVR[3] = uut.SVR_WVR[3];
    assign SVR_WVR[4] = uut.SVR_WVR[4];
    assign SVR_WVR[5] = uut.SVR_WVR[5];
    assign SVR_WVR[6] = uut.SVR_WVR[6];
    assign SVR_WVR[7] = uut.SVR_WVR[7];
    assign SVR_WVR[8] = uut.SVR_WVR[8];
    assign SVR_WVR[9] = uut.SVR_WVR[9];
    assign SVR_WVR[10] = uut.SVR_WVR[10];
    assign SVR_WVR[11] = uut.SVR_WVR[11];
    assign SVR_WVR[12] = uut.SVR_WVR[12];
    assign SVR_WVR[13] = uut.SVR_WVR[13];
    assign SVR_WVR[14] = uut.SVR_WVR[14];
    assign SVR_WVR[15] = uut.SVR_WVR[15];
    assign SVR_WVR[16] = uut.SVR_WVR[16];
    assign SVR_WVR[17] = uut.SVR_WVR[17];
    assign SVR_WVR[18] = uut.SVR_WVR[18];
    assign SVR_WVR[19] = uut.SVR_WVR[19];
    assign SVR_WVR[20] = uut.SVR_WVR[20];
    assign SVR_WVR[21] = uut.SVR_WVR[21];
    assign SVR_WVR[22] = uut.SVR_WVR[22];
    assign SVR_WVR[23] = uut.SVR_WVR[23];
    assign SVR_WVR[24] = uut.SVR_WVR[24];
    assign SVR_WVR[25] = uut.SVR_WVR[25];
    assign SVR_WVR[26] = uut.SVR_WVR[26];
    assign SVR_WVR[27] = uut.SVR_WVR[27];
    assign SVR_WVR[28] = uut.SVR_WVR[28];
    assign SVR_WVR[29] = uut.SVR_WVR[29];
    assign SVR_WVR[30] = uut.SVR_WVR[30];
    assign SVR_WVR[31] = uut.SVR_WVR[31];


    // Clock generation
    initial begin
        clk = 0;
        forever #5 clk = ~clk; // 10 time units clock period
    end

    // Initialize instruction memory
    initial begin
        uut.instruction_memory[0] = 32'b000011100000_00000_001_1_0000_0000001; 
        uut.instruction_memory[1] = 32'b000000000100_00001_010_0_0001_0000001; 
        uut.instruction_memory[2] = 32'b000100011000_00010_100_1_0010_0000001; 
        uut.instruction_memory[3] = 32'b000000010000_00011_001_0_0011_0000010;
        uut.instruction_memory[4] = 32'b000001010000_00100_010_1_0100_0000010; 
        uut.instruction_memory[5] = 32'b101100000000_00101_100_0_0101_0000010;
    end

    // Assert RESET for one clock cycle
    initial begin
        reset = 1; 
        #10;       
        reset = 0; 
    end
    
     // Monitoring Signals 
    initial begin
        $monitor(
            "Time: %0dns | PC: %0d | IF_ID_instr: %h | IF_ID_PC: %d | ID_EX_PC: %d | ID_EX_instr: %h | ID_EX_read_data: %d | ID_EX_rd: %d | ID_EX_rs1: %d | ID_EX_hint: %b | ID_EX_imm: %d | ID_EX_funct3: %b | EX_MEM_alu_result: %d | EX_MEM_rd: %d | EX_MEM_hint: %b | EX_MEM_funct3: %b | MEM_WB_alu_result: %d | MEM_WB_rd: %d | MEM_WB_memOut[0]: %d | MEM_WB_memOut[1]: %d | MEM_WB_memOut[2]: %d | MEM_WB_memOut[3]: %d | MEM_WB_memOut[4]: %d | MEM_WB_memOut[5]: %d | MEM_WB_memOut[6]: %d | MEM_WB_memOut[7]: %d | MEM_WB_memOut[8]: %d | MEM_WB_memOut[9]: %d | MEM_WB_memOut[10]: %d | MEM_WB_memOut[11]: %d | MEM_WB_memOut[12]: %d | MEM_WB_memOut[13]: %d | MEM_WB_memOut[14]: %d | MEM_WB_memOut[15]: %d | SVR_WVR[0]: %d | SVR_WVR[1]: %d | SVR_WVR[2]: %d | SVR_WVR[3]: %d | SVR_WVR[4]: %d | SVR_WVR[5]: %d | SVR_WVR[6]: %d | SVR_WVR[7]: %d | SVR_WVR[8]: %d | SVR_WVR[9]: %d | SVR_WVR[10]: %d | SVR_WVR[11]: %d | SVR_WVR[12]: %d | SVR_WVR[13]: %d | SVR_WVR[14]: %d | SVR_WVR[15]: %d | SVR_WVR[16]: %d | SVR_WVR[17]: %d | SVR_WVR[18]: %d | SVR_WVR[19]: %d | SVR_WVR[20]: %d | SVR_WVR[21]: %d | SVR_WVR[22]: %d | SVR_WVR[23]: %d | SVR_WVR[24]: %d | SVR_WVR[25]: %d | SVR_WVR[26]: %d | SVR_WVR[27]: %d | SVR_WVR[28]: %d | SVR_WVR[29]: %d | SVR_WVR[30]: %d | SVR_WVR[31]: %d",
            $time,
            uut.PC,
            uut.IF_ID_instr,
            uut.IF_ID_PC,
            uut.ID_EX_PC,
            uut.ID_EX_instr,
            uut.ID_EX_read_data,
            uut.ID_EX_rd,
            uut.ID_EX_rs1,
            uut.ID_EX_hint,
            uut.ID_EX_imm,
            uut.ID_EX_funct3,
            uut.EX_MEM_alu_result,
            uut.EX_MEM_rd,
            uut.EX_MEM_hint,
            uut.EX_MEM_funct3,
            uut.MEM_WB_alu_result,
            uut.MEM_WB_rd,
            uut.MEM_WB_memOut[0],
            uut.MEM_WB_memOut[1],
            uut.MEM_WB_memOut[2],
            uut.MEM_WB_memOut[3],
            uut.MEM_WB_memOut[4],
            uut.MEM_WB_memOut[5],
            uut.MEM_WB_memOut[6],
            uut.MEM_WB_memOut[7],
            uut.MEM_WB_memOut[8],
            uut.MEM_WB_memOut[9],
            uut.MEM_WB_memOut[10],
            uut.MEM_WB_memOut[11],
            uut.MEM_WB_memOut[12],
            uut.MEM_WB_memOut[13],
            uut.MEM_WB_memOut[14],
            uut.MEM_WB_memOut[15],
            uut.SVR_WVR[0],
            uut.SVR_WVR[1],
            uut.SVR_WVR[2],
            uut.SVR_WVR[3],
            uut.SVR_WVR[4],
            uut.SVR_WVR[5],
            uut.SVR_WVR[6],
            uut.SVR_WVR[7],
            uut.SVR_WVR[8],
            uut.SVR_WVR[9],
            uut.SVR_WVR[10],
            uut.SVR_WVR[11],
            uut.SVR_WVR[12],
            uut.SVR_WVR[13],
            uut.SVR_WVR[14],
            uut.SVR_WVR[15],
            uut.SVR_WVR[16],
            uut.SVR_WVR[17],
            uut.SVR_WVR[18],
            uut.SVR_WVR[19],
            uut.SVR_WVR[20],
            uut.SVR_WVR[21],
            uut.SVR_WVR[22],
            uut.SVR_WVR[23],
            uut.SVR_WVR[24],
            uut.SVR_WVR[25],
            uut.SVR_WVR[26],
            uut.SVR_WVR[27],
            uut.SVR_WVR[28],
            uut.SVR_WVR[29],
            uut.SVR_WVR[30],
            uut.SVR_WVR[31]
        );
    end

    // Simulation time
    initial begin
        #200; 
        $finish; 
    end
endmodule

riscv_test/riscv_test.sim/sim_1/behav/xsim/riscv_pipeline.vcd
$date
   Tue Oct 22 11:28:00 2024
$end
$version
  2022.1
$end
$timescale
  1ps
$end
$scope module tb_riscv_pipeline_basic $end
$var reg 1 ! clk $end
$var reg 1 " reset $end
$var wire 32 # PC [31:0] $end
$var wire 32 $ IF_ID_instr [31:0] $end
$var wire 32 % IF_ID_PC [31:0] $end
$var wire 32 & ID_EX_PC [31:0] $end
$var wire 32 ' ID_EX_instr [31:0] $end
$var wire 32 ( ID_EX_read_data [31:0] $end
$var wire 5 ) ID_EX_rs1 [4:0] $end
$var wire 5 * ID_EX_rd [4:0] $end
$var wire 1 + ID_EX_hint $end
$var wire 12 , ID_EX_imm [11:0] $end
$var wire 3 - ID_EX_funct3 [2:0] $end
$var wire 32 . EX_MEM_alu_result [31:0] $end
$var wire 5 / EX_MEM_rd [4:0] $end
$var wire 1 0 EX_MEM_hint $end
$var wire 3 1 EX_MEM_funct3 [2:0] $end
$var wire 32 2 MEM_WB_alu_result [31:0] $end
$var wire 5 3 MEM_WB_rd [4:0] $end
$scope module uut $end
$var wire 1 4 clk $end
$var wire 1 5 reset $end
$var reg 32 6 IF_ID_instr [31:0] $end
$var reg 32 7 IF_ID_PC [31:0] $end
$var reg 32 8 ID_EX_PC [31:0] $end
$var reg 32 9 ID_EX_instr [31:0] $end
$var reg 32 : ID_EX_read_data [31:0] $end
$var reg 5 ; ID_EX_rs1 [4:0] $end
$var reg 5 < ID_EX_rd [4:0] $end
$var reg 1 = ID_EX_hint [0:0] $end
$var reg 12 > ID_EX_imm [11:0] $end
$var reg 3 ? ID_EX_funct3 [2:0] $end
$var reg 32 @ EX_MEM_alu_result [31:0] $end
$var reg 5 A EX_MEM_rd [4:0] $end
$var reg 1 B EX_MEM_hint [0:0] $end
$var reg 3 C EX_MEM_funct3 [2:0] $end
$var reg 32 D MEM_WB_alu_result [31:0] $end
$var reg 5 E MEM_WB_rd [4:0] $end
$var reg 3 F MEM_WB_funct3 [2:0] $end
$var reg 32 G PC [31:0] $end
$var integer 32 H i [31:0] $end
$var wire 7 I opcode [6:0] $end
$var wire 5 J rd [4:0] $end
$var wire 1 K hint [0:0] $end
$var wire 3 L funct3 [2:0] $end
$var wire 5 M rs1 [4:0] $end
$var wire 12 N imm [11:0] $end
$var wire 32 O alu_input1 [31:0] $end
$var wire 32 P alu_input2 [31:0] $end
$var reg 32 Q alu_result [31:0] $end
$var reg 4 R SVR_WVR_Addr [3:0] $end
$upscope $end
$upscope $end
$enddefinitions $end
#0
$dumpvars
0!
1"
b0 #
b0 $
b0 %
b0 &
b0 '
bx (
bx )
bx *
x+
bx ,
bx -
b0 .
bx /
x0
bx 1
b0 2
bx 3
04
15
b0 6
b0 7
b0 8
b0 9
bx :
bx ;
bx <
x=
bx >
bx ?
b0 @
bx A
xB
bx C
b0 D
bx E
bx F
b0 G
b100000000 H
b0 I
b0 J
0K
b0 L
b0 M
b0 N
bx O
b0xxxxxxxxxxxx P
bx Q
bx R
$end
#5000
1!
14
#10000
0!
0"
04
05
#15000
1!
b1 #
b1110000000000001100000000001 $
b0 (
b0 )
b0 *
0+
b0 ,
b0 -
bx .
14
b1110000000000001100000000001 6
b0 :
b0 ;
b0 <
0=
b0 >
b0 ?
bx @
b1 G
b1 I
b10000 J
1K
b1 L
b11100000 N
b0 O
b0 P
b0 Q
#20000
0!
04
#25000
1!
b10 #
b10000001010000010000001 $
b1 %
b1110000000000001100000000001 '
b10000 *
1+
b11100000 ,
b1 -
b0 .
b0 /
00
b0 1
bx 2
14
b10000001010000010000001 6
b1 7
b1110000000000001100000000001 9
b10000 <
1=
b11100000 >
b1 ?
b0 @
b0 A
0B
b0 C
bx D
b10 G
b10001 J
0K
b10 L
b1 M
b100 N
b11100000 P
b11100000 Q
#30000
0!
04
#35000
1!
b11 #
b10001100000010100100100000001 $
b10 %
b1 &
b10000001010000010000001 '
b1 (
b1 )
b10001 *
0+
b100 ,
b10 -
b11100000 .
b10000 /
10
b1 1
b0 2
b0 3
14
b10001100000010100100100000001 6
b10 7
b1 8
b10000001010000010000001 9
b1 :
b1 ;
b10001 <
0=
b100 >
b10 ?
b11100000 @
b10000 A
1B
b1 C
b0 D
b0 E
b0 F
b11 G
b10010 J
1K
b100 L
b10 M
b100011000 N
b1 O
b100 P
b101 Q
#40000
0!
04
#45000
1!
b100 #
b1000000011001000110000010 $
b11 %
b10 &
b10001100000010100100100000001 '
b10 (
b10 )
b10010 *
1+
b100011000 ,
b100 -
b101 .
b10001 /
00
b10 1
b11100000 2
b10000 3
14
b1000000011001000110000010 6
b11 7
b10 8
b10001100000010100100100000001 9
b10 :
b10 ;
b10010 <
1=
b100011000 >
b100 ?
b101 @
b10001 A
0B
b10 C
b11100000 D
b10000 E
b1 F
b100 G
b100 H
b10 I
b11 J
0K
b1 L
b11 M
b10000 N
b10 O
b100011000 P
b100011010 Q
#50000
0!
04
#55000
1!
b101 #
b101000000100010101000000010 $
b100 %
b11 &
b1000000011001000110000010 '
b11 (
b11 )
b11 *
0+
b10000 ,
b1 -
b100011010 .
b10010 /
10
b100 1
b101 2
b10001 3
14
b101000000100010101000000010 6
b100 7
b11 8
b1000000011001000110000010 9
b11 :
b11 ;
b11 <
0=
b10000 >
b1 ?
b100011010 @
b10010 A
1B
b100 C
b101 D
b10001 E
b10 F
b101 G
b100 H
b100 J
1K
b10 L
b100 M
b1010000 N
b11 O
b10000 P
b10011 Q
b100 R
#60000
0!
04
#65000
1!
b110 #
b10110000000000101100001010000010 $
b101 %
b100 &
b101000000100010101000000010 '
b100 (
b100 )
b100 *
1+
b1010000 ,
b10 -
b10011 .
b11 /
00
b1 1
b100011010 2
b10010 3
14
b10110000000000101100001010000010 6
b101 7
b100 8
b101000000100010101000000010 9
b100 :
b100 ;
b100 <
1=
b1010000 >
b10 ?
b10011 @
b11 A
0B
b1 C
b100011010 D
b10010 E
b100 F
b110 G
b10000 H
b101 J
0K
b100 L
b101 M
b101100000000 N
b100 O
b1010000 P
b1010100 Q
b1 R
#70000
0!
04
#75000
1!
b111 #
bx $
b110 %
b101 &
b10110000000000101100001010000010 '
b101 (
b101 )
b101 *
0+
b101100000000 ,
b100 -
b1010100 .
b100 /
10
b10 1
b10011 2
b11 3
14
bx 6
b110 7
b101 8
b10110000000000101100001010000010 9
b101 :
b101 ;
b101 <
0=
b101100000000 >
b100 ?
b1010100 @
b100 A
1B
b10 C
b10011 D
b11 E
b1 F
b111 G
b100 H
bx I
bx J
xK
bx L
bx M
bx N
b101 O
b101100000000 P
b101100000101 Q
#80000
0!
04
#85000
1!
b1000 #
b111 %
b110 &
bx '
bx (
bx )
bx *
x+
bx ,
bx -
b101100000101 .
b101 /
00
b100 1
b1010100 2
b100 3
14
b111 7
b110 8
bx 9
bx :
bx ;
bx <
x=
bx >
bx ?
b101100000101 @
b101 A
0B
b100 C
b1010100 D
b100 E
b10 F
b1000 G
b100 H
bx O
b0xxxxxxxxxxxx P
bx Q
b111 R
#90000
0!
04
#95000
1!
b1001 #
b1000 %
b111 &
bx .
bx /
x0
bx 1
b101100000101 2
b101 3
14
b1000 7
b111 8
bx @
bx A
xB
bx C
b101100000101 D
b101 E
b100 F
b1001 G
b10000 H
b100 R
#100000
0!
04
#105000
1!
b1010 #
b1001 %
b1000 &
bx 2
bx 3
14
b1001 7
b1000 8
bx D
bx E
bx F
b1010 G
#110000
0!
04
#115000
1!
b1011 #
b1010 %
b1001 &
14
b1010 7
b1001 8
b1011 G
#120000
0!
04
#125000
1!
b1100 #
b1011 %
b1010 &
14
b1011 7
b1010 8
b1100 G
#130000
0!
04
#135000
1!
b1101 #
b1100 %
b1011 &
14
b1100 7
b1011 8
b1101 G
#140000
0!
04
#145000
1!
b1110 #
b1101 %
b1100 &
14
b1101 7
b1100 8
b1110 G
#150000
0!
04
#155000
1!
b1111 #
b1110 %
b1101 &
14
b1110 7
b1101 8
b1111 G
#160000
0!
04
#165000
1!
b10000 #
b1111 %
b1110 &
14
b1111 7
b1110 8
b10000 G
#170000
0!
04
#175000
1!
b10001 #
b10000 %
b1111 &
14
b10000 7
b1111 8
b10001 G
#180000
0!
04
#185000
1!
b10010 #
b10001 %
b10000 &
14
b10001 7
b10000 8
b10010 G
#190000
0!
04
#195000
1!
b10011 #
b10010 %
b10001 &
14
b10010 7
b10001 8
b10011 G
