riscv_test/riscv_test.srcs/sources_1/new/top.v
module riscv_pipeline_basic (
    input clk,
    input reset
);

    // Instruction memory, register file, SVR_WVR, and data memory
    reg [31:0] instruction_memory [0:255];  // 256 instructions
    reg [31:0] data_memory [0:255];         // 256 words of data
    reg [31:0] register_file [0:31];        // 32 general-purpose registers
    reg [31:0] SVR_WVR [0:31];              // 16 SVR, 16 WVR

    // Pipeline registers
    reg [31:0] IF_ID_instr, IF_ID_PC;
    
    reg [31:0] ID_EX_PC, ID_EX_instr;
    reg [31:0] ID_EX_read_data;
    reg [4:0] ID_EX_rs1, ID_EX_rd;
    reg [0:0] ID_EX_hint;
    reg [11:0] ID_EX_imm;
    reg [2:0] ID_EX_funct3;
    
    reg [31:0] EX_MEM_alu_result;
    reg [4:0]  EX_MEM_rd;
    reg [0:0] EX_MEM_hint;
    reg [2:0] EX_MEM_funct3;
    
    reg [31:0] MEM_WB_alu_result;
    reg [4:0]  MEM_WB_rd;
    reg [2:0] MEM_WB_funct3;
    reg [31:0] MEM_WB_memOut [15:0];

    // Program Counter (PC)
    reg [31:0] PC;

    // Iterator 
    integer i;

    // Initialize components
    initial begin
        PC = 0;
       
        // Initialize the register file
        for (i = 0; i < 32; i = i + 1) begin
            register_file[i] <= i;
        end
        
        // Initialize the data memory
        for (i = 0; i < 256; i = i + 1) begin
            data_memory[i] <= i;
        end
    end

    // FETCH stage
    always @(posedge clk or posedge reset) begin
        if (reset) begin
            IF_ID_instr <= 0;
            IF_ID_PC <= 0;
        end else begin
            IF_ID_instr <= instruction_memory[PC[7:0]];  // Fetch instruction
            IF_ID_PC <= PC;
            PC <= PC + 1;  // Increment PC
        end
    end

    // DECODE stage
    wire [6:0] opcode = IF_ID_instr[6:0];
    wire [4:0] rd = {(IF_ID_instr[0]), IF_ID_instr[10:7]};
    wire [0:0] hint = IF_ID_instr[11];
    wire [2:0] funct3 = IF_ID_instr[14:12];
    wire [4:0] rs1 = IF_ID_instr[19:15];
    wire [11:0] imm = IF_ID_instr[31:20];

    always @(posedge clk or posedge reset) begin
        if (reset) begin
            ID_EX_PC <= 0;
            ID_EX_instr <= 0;
        end else begin
            ID_EX_PC <= IF_ID_PC;
            ID_EX_instr <= IF_ID_instr;
            ID_EX_rd <= rd;
            ID_EX_read_data <= register_file[rs1];
            ID_EX_rs1 <= rs1;
            ID_EX_hint <= hint;
            ID_EX_imm <= imm;
            ID_EX_funct3 <= funct3;
        end
    end

    // EXECUTE stage
    wire [31:0] alu_input1 = ID_EX_read_data;
    wire [31:0] alu_input2 = ID_EX_imm;
    reg [31:0] alu_result = 0;

    always @(*) begin
        alu_result = alu_input1 + alu_input2;  
    end

    always @(posedge clk or posedge reset) begin
        if (reset) begin
            EX_MEM_alu_result <= 0;
        end else begin
            EX_MEM_alu_result <= alu_result;
            EX_MEM_rd <= ID_EX_rd;
            EX_MEM_hint <= ID_EX_hint;
            EX_MEM_funct3 <= ID_EX_funct3;
        end
    end

    // MEMORY stage
    reg [31:0] memOut [15:0];
    
    always @ (*) begin
        case(EX_MEM_funct3)
            3'b001: begin 
                    memOut[EX_MEM_rd[3:0]] = data_memory[EX_MEM_alu_result%256];
                end
            3'b010: begin
                    for (i = 0; i < 4; i = i + 1) begin
                        memOut[(EX_MEM_rd[3:0] + i)%16] = data_memory[(EX_MEM_alu_result + i)%256];
                    end
                end
            3'b100: begin
                    for (i = 0; i < 16; i = i + 1) begin
                        memOut[(EX_MEM_rd[3:0] + i)%16] = data_memory[(EX_MEM_alu_result + i)%256];
                    end
                end
        endcase
    end
    
    always @(posedge clk or posedge reset) begin
        if (reset) begin
            MEM_WB_alu_result <= 0;
        end else begin
            MEM_WB_alu_result <= EX_MEM_alu_result;
            MEM_WB_rd <= EX_MEM_rd;
            MEM_WB_funct3 <= EX_MEM_funct3;
            
            for (i = 0; i < 16; i = i + 1) begin
                MEM_WB_memOut[i] <= memOut[i];
            end
        end
    end

    // WRITEBACK stage
    reg [3:0] SVR_WVR_Addr; 
    
    always @ (*) begin
        if (!reset) begin   
            case(MEM_WB_funct3)
                3'b001: begin 
                        SVR_WVR[MEM_WB_rd] = MEM_WB_memOut[MEM_WB_rd[3:0]];
                    end
                3'b010: begin
                    for (i = 0; i < 4; i = i + 1) begin
                        SVR_WVR_Addr = ((MEM_WB_rd[3:0] + i)%16);
                        SVR_WVR[{MEM_WB_rd[4],SVR_WVR_Addr}] = MEM_WB_memOut[(MEM_WB_rd[3:0] + i)%16];
                    end
                end
                3'b100: begin
                    for (i = 0; i < 16; i = i + 1) begin
                        SVR_WVR_Addr = ((MEM_WB_rd[3:0] + i)%16);
                        SVR_WVR[{MEM_WB_rd[4],SVR_WVR_Addr}] = MEM_WB_memOut[(MEM_WB_rd[3:0] + i)%16];
                    end
                end
            endcase
        end 
    end

endmodule

riscv_test/riscv_test.srcs/sim_1/new/tb_riscv_pipeline.v
`timescale 1ns / 1ps

module tb_riscv_pipeline_basic;
    reg clk;
    reg reset;

    // Instantiate the RISC-V pipeline module
    riscv_pipeline_basic uut (
        .clk(clk),
        .reset(reset)
    );

    // Clock generation
    initial begin
        clk = 0;
        forever #5 clk = ~clk; // 10 time units clock period
    end

    // Initialize memory and registers to specific values
    initial begin
        // Initialize some instructions in the instruction memory
        uut.instruction_memory[0] = 32'b000011100000_00000_001_1_0000_0000001; 
        uut.instruction_memory[1] = 32'b000000000100_00001_010_0_0001_0000001; 
        uut.instruction_memory[2] = 32'b000100011000_00010_100_1_0010_0000001; 
        uut.instruction_memory[3] = 32'b000000010000_00011_001_0_0011_0000010;
        uut.instruction_memory[4] = 32'b000001010000_00100_010_1_0100_0000010; 
        uut.instruction_memory[5] = 32'b101100000000_00101_100_0_0101_0000010;
    end

    // Reset sequence
    initial begin
        reset = 1; // Assert reset
        #10;       // Hold reset for 10 time units
        reset = 0; // Deassert reset
    end

    // VCD file generation
    initial begin
        $dumpfile("riscv_pipeline.vcd"); // Specify the VCD file name
        $dumpvars(0, tb_riscv_pipeline_basic); // Dump all variables in the module and its submodules
    end

    // Monitoring signals including SVR_WVR registers
    initial begin
        // Monitor the relevant signals and all entries in SVR_WVR
        $monitor(
            "Time: %0dns | PC: %0d | IF_ID_instr: %h | IF_ID_PC: %d | ID_EX_PC: %d | ID_EX_instr: %h | ID_EX_read_data: %d | ID_EX_rd: %d | ID_EX_rs1: %d | ID_EX_hint: %b | ID_EX_imm: %d | ID_EX_funct3: %b | EX_MEM_alu_result: %d | EX_MEM_rd: %d | EX_MEM_hint: %b | EX_MEM_funct3: %b | MEM_WB_alu_result: %d | MEM_WB_rd: %d | MEM_WB_memOut[0]: %d | MEM_WB_memOut[1]: %d | MEM_WB_memOut[2]: %d | MEM_WB_memOut[3]: %d | MEM_WB_memOut[4]: %d | MEM_WB_memOut[5]: %d | MEM_WB_memOut[6]: %d | MEM_WB_memOut[7]: %d | MEM_WB_memOut[8]: %d | MEM_WB_memOut[9]: %d | MEM_WB_memOut[10]: %d | MEM_WB_memOut[11]: %d | MEM_WB_memOut[12]: %d | MEM_WB_memOut[13]: %d | MEM_WB_memOut[14]: %d | MEM_WB_memOut[15]: %d | SVR_WVR[0]: %d | SVR_WVR[1]: %d | SVR_WVR[2]: %d | SVR_WVR[3]: %d | SVR_WVR[4]: %d | SVR_WVR[5]: %d | SVR_WVR[6]: %d | SVR_WVR[7]: %d | SVR_WVR[8]: %d | SVR_WVR[9]: %d | SVR_WVR[10]: %d | SVR_WVR[11]: %d | SVR_WVR[12]: %d | SVR_WVR[13]: %d | SVR_WVR[14]: %d | SVR_WVR[15]: %d | SVR_WVR[16]: %d | SVR_WVR[17]: %d | SVR_WVR[18]: %d | SVR_WVR[19]: %d | SVR_WVR[20]: %d | SVR_WVR[21]: %d | SVR_WVR[22]: %d | SVR_WVR[23]: %d | SVR_WVR[24]: %d | SVR_WVR[25]: %d | SVR_WVR[26]: %d | SVR_WVR[27]: %d | SVR_WVR[28]: %d | SVR_WVR[29]: %d | SVR_WVR[30]: %d | SVR_WVR[31]: %d",
            $time,
            uut.PC,
            uut.IF_ID_instr,
            uut.IF_ID_PC,
            uut.ID_EX_PC,
            uut.ID_EX_instr,
            uut.ID_EX_read_data,
            uut.ID_EX_rd,
            uut.ID_EX_rs1,
            uut.ID_EX_hint,
            uut.ID_EX_imm,
            uut.ID_EX_funct3,
            uut.EX_MEM_alu_result,
            uut.EX_MEM_rd,
            uut.EX_MEM_hint,
            uut.EX_MEM_funct3,
            uut.MEM_WB_alu_result,
            uut.MEM_WB_rd,
            uut.MEM_WB_memOut[0],
            uut.MEM_WB_memOut[1],
            uut.MEM_WB_memOut[2],
            uut.MEM_WB_memOut[3],
            uut.MEM_WB_memOut[4],
            uut.MEM_WB_memOut[5],
            uut.MEM_WB_memOut[6],
            uut.MEM_WB_memOut[7],
            uut.MEM_WB_memOut[8],
            uut.MEM_WB_memOut[9],
            uut.MEM_WB_memOut[10],
            uut.MEM_WB_memOut[11],
            uut.MEM_WB_memOut[12],
            uut.MEM_WB_memOut[13],
            uut.MEM_WB_memOut[14],
            uut.MEM_WB_memOut[15],
            uut.SVR_WVR[0],
            uut.SVR_WVR[1],
            uut.SVR_WVR[2],
            uut.SVR_WVR[3],
            uut.SVR_WVR[4],
            uut.SVR_WVR[5],
            uut.SVR_WVR[6],
            uut.SVR_WVR[7],
            uut.SVR_WVR[8],
            uut.SVR_WVR[9],
            uut.SVR_WVR[10],
            uut.SVR_WVR[11],
            uut.SVR_WVR[12],
            uut.SVR_WVR[13],
            uut.SVR_WVR[14],
            uut.SVR_WVR[15],
            uut.SVR_WVR[16],
            uut.SVR_WVR[17],
            uut.SVR_WVR[18],
            uut.SVR_WVR[19],
            uut.SVR_WVR[20],
            uut.SVR_WVR[21],
            uut.SVR_WVR[22],
            uut.SVR_WVR[23],
            uut.SVR_WVR[24],
            uut.SVR_WVR[25],
            uut.SVR_WVR[26],
            uut.SVR_WVR[27],
            uut.SVR_WVR[28],
            uut.SVR_WVR[29],
            uut.SVR_WVR[30],
            uut.SVR_WVR[31]
        );
    end

    // Simulation time
    initial begin
        #200; // Run the simulation for 200 time units
        $finish; // End simulation
    end
endmodule

riscv_test/riscv_test.sim/sim_1/behav/xsim/riscv_pipeline.vcd
$date
   Mon Oct 21 00:29:09 2024
$end
$version
  2022.1
$end
$timescale
  1ps
$end
$scope module tb_riscv_pipeline_basic $end
$var reg 1 ! clk $end
$var reg 1 " reset $end
$scope module uut $end
$var wire 1 # clk $end
$var wire 1 $ reset $end
$var reg 32 % IF_ID_instr [31:0] $end
$var reg 32 & IF_ID_PC [31:0] $end
$var reg 32 ' ID_EX_PC [31:0] $end
$var reg 32 ( ID_EX_instr [31:0] $end
$var reg 32 ) ID_EX_read_data [31:0] $end
$var reg 5 * ID_EX_rs1 [4:0] $end
$var reg 5 + ID_EX_rd [4:0] $end
$var reg 1 , ID_EX_hint [0:0] $end
$var reg 12 - ID_EX_imm [11:0] $end
$var reg 3 . ID_EX_funct3 [2:0] $end
$var reg 32 / EX_MEM_alu_result [31:0] $end
$var reg 5 0 EX_MEM_rd [4:0] $end
$var reg 1 1 EX_MEM_hint [0:0] $end
$var reg 3 2 EX_MEM_funct3 [2:0] $end
$var reg 32 3 MEM_WB_alu_result [31:0] $end
$var reg 5 4 MEM_WB_rd [4:0] $end
$var reg 3 5 MEM_WB_funct3 [2:0] $end
$var reg 32 6 PC [31:0] $end
$var integer 32 7 i [31:0] $end
$var wire 7 8 opcode [6:0] $end
$var wire 5 9 rd [4:0] $end
$var wire 1 : hint [0:0] $end
$var wire 3 ; funct3 [2:0] $end
$var wire 5 < rs1 [4:0] $end
$var wire 12 = imm [11:0] $end
$var wire 32 > alu_input1 [31:0] $end
$var wire 32 ? alu_input2 [31:0] $end
$var reg 32 @ alu_result [31:0] $end
$var reg 4 A SVR_WVR_Addr [3:0] $end
$upscope $end
$upscope $end
$enddefinitions $end
#0
$dumpvars
0!
1"
0#
1$
b0 %
b0 &
b0 '
b0 (
bx )
bx *
bx +
x,
bx -
bx .
b0 /
bx 0
x1
bx 2
b0 3
bx 4
bx 5
b0 6
b100000000 7
b0 8
b0 9
0:
b0 ;
b0 <
b0 =
bx >
b0xxxxxxxxxxxx ?
bx @
bx A
$end
#5000
1!
1#
#10000
0!
0"
0#
0$
#15000
1!
1#
b1110000000000001100000000001 %
b0 )
b0 *
b0 +
0,
b0 -
b0 .
bx /
b1 6
b1 8
b10000 9
1:
b1 ;
b11100000 =
b0 >
b0 ?
b0 @
#20000
0!
0#
#25000
1!
1#
b10000001010000010000001 %
b1 &
b1110000000000001100000000001 (
b10000 +
1,
b11100000 -
b1 .
b0 /
b0 0
01
b0 2
bx 3
b10 6
b10001 9
0:
b10 ;
b1 <
b100 =
b11100000 ?
b11100000 @
#30000
0!
0#
#35000
1!
1#
b10001100000010100100100000001 %
b10 &
b1 '
b10000001010000010000001 (
b1 )
b1 *
b10001 +
0,
b100 -
b10 .
b11100000 /
b10000 0
11
b1 2
b0 3
b0 4
b0 5
b11 6
b10010 9
1:
b100 ;
b10 <
b100011000 =
b1 >
b100 ?
b101 @
#40000
0!
0#
#45000
1!
1#
b1000000011001000110000010 %
b11 &
b10 '
b10001100000010100100100000001 (
b10 )
b10 *
b10010 +
1,
b100011000 -
b100 .
b101 /
b10001 0
01
b10 2
b11100000 3
b10000 4
b1 5
b100 6
b100 7
b10 8
b11 9
0:
b1 ;
b11 <
b10000 =
b10 >
b100011000 ?
b100011010 @
#50000
0!
0#
#55000
1!
1#
b101000000100010101000000010 %
b100 &
b11 '
b1000000011001000110000010 (
b11 )
b11 *
b11 +
0,
b10000 -
b1 .
b100011010 /
b10010 0
11
b100 2
b101 3
b10001 4
b10 5
b101 6
b100 7
b100 9
1:
b10 ;
b100 <
b1010000 =
b11 >
b10000 ?
b10011 @
b100 A
#60000
0!
0#
#65000
1!
1#
b10110000000000101100001010000010 %
b101 &
b100 '
b101000000100010101000000010 (
b100 )
b100 *
b100 +
1,
b1010000 -
b10 .
b10011 /
b11 0
01
b1 2
b100011010 3
b10010 4
b100 5
b110 6
b10000 7
b101 9
0:
b100 ;
b101 <
b101100000000 =
b100 >
b1010000 ?
b1010100 @
b1 A
#70000
0!
0#
#75000
1!
1#
bx %
b110 &
b101 '
b10110000000000101100001010000010 (
b101 )
b101 *
b101 +
0,
b101100000000 -
b100 .
b1010100 /
b100 0
11
b10 2
b10011 3
b11 4
b1 5
b111 6
b100 7
bx 8
bx 9
x:
bx ;
bx <
bx =
b101 >
b101100000000 ?
b101100000101 @
#80000
0!
0#
#85000
1!
1#
b111 &
b110 '
bx (
bx )
bx *
bx +
x,
bx -
bx .
b101100000101 /
b101 0
01
b100 2
b1010100 3
b100 4
b10 5
b1000 6
b100 7
bx >
b0xxxxxxxxxxxx ?
bx @
b111 A
#90000
0!
0#
#95000
1!
1#
b1000 &
b111 '
bx /
bx 0
x1
bx 2
b101100000101 3
b101 4
b100 5
b1001 6
b10000 7
b100 A
#100000
0!
0#
#105000
1!
1#
b1001 &
b1000 '
bx 3
bx 4
bx 5
b1010 6
#110000
0!
0#
#115000
1!
1#
b1010 &
b1001 '
b1011 6
#120000
0!
0#
#125000
1!
1#
b1011 &
b1010 '
b1100 6
#130000
0!
0#
#135000
1!
1#
b1100 &
b1011 '
b1101 6
#140000
0!
0#
#145000
1!
1#
b1101 &
b1100 '
b1110 6
#150000
0!
0#
#155000
1!
1#
b1110 &
b1101 '
b1111 6
#160000
0!
0#
#165000
1!
1#
b1111 &
b1110 '
b10000 6
#170000
0!
0#
#175000
1!
1#
b10000 &
b1111 '
b10001 6
#180000
0!
0#
#185000
1!
1#
b10001 &
b10000 '
b10010 6
#190000
0!
0#
#195000
1!
1#
b10010 &
b10001 '
b10011 6
